mcstatus/__init__.py
mcstatus/__main__.py
mcstatus/address.py
mcstatus/bedrock_status.py
mcstatus/dns.py
mcstatus/forge_data.py
mcstatus/pinger.py
mcstatus/py.typed
mcstatus/querier.py
mcstatus/responses.py
mcstatus/server.py
mcstatus/status_response.py
mcstatus/utils.py
mcstatus/motd/__init__.py
mcstatus/motd/components.py
mcstatus/motd/simplifies.py
mcstatus/motd/transformers.py
mcstatus/protocol/__init__.py
mcstatus/protocol/connection.py
mcstatus-12.0.4.dist-info/METADATA
mcstatus-12.0.4.dist-info/WHEEL
mcstatus-12.0.4.dist-info/entry_points.txt
mcstatus-12.0.4.dist-info/licenses/LICENSE
mcstatus-12.0.4.dist-info/RECORD
