Metadata-Version: 2.4
Name: mcstatus
Version: 12.0.4
Summary: A library to query Minecraft Servers for their status and capabilities.
Project-URL: Documentation, https://mcstatus.readthedocs.io
Project-URL: Source code, https://github.com/py-mine/mcstatus
Author-email: Nathan Adams <dinnerbone@dinnerbone.com>, ItsDrike <itsdrike@protonmail.com>, PerchunPak <perchunpak@gmail.com>
Maintainer-email: Kevin Tindall <kevinkjt2000@gmail.com>, ItsDrike <itsdrike@protonmail.com>, PerchunPak <perchunpak@gmail.com>
License-Expression: Apache-2.0
License-File: LICENSE
Keywords: minecraft,protocol
Classifier: Development Status :: 5 - Production/Stable
Classifier: Intended Audience :: Developers
Classifier: License :: OSI Approved :: Apache Software License
Classifier: Natural Language :: English
Classifier: Operating System :: OS Independent
Classifier: Programming Language :: Python
Classifier: Programming Language :: Python :: 3
Classifier: Programming Language :: Python :: 3.9
Classifier: Programming Language :: Python :: 3.10
Classifier: Programming Language :: Python :: 3.11
Classifier: Programming Language :: Python :: 3.12
Classifier: Programming Language :: Python :: 3.13
Classifier: Topic :: Games/Entertainment
Classifier: Topic :: Software Development :: Libraries :: Python Modules
Classifier: Topic :: System :: Monitoring
Classifier: Typing :: Typed
Requires-Python: >=3.9
Requires-Dist: asyncio-dgram>=2.1.2
Requires-Dist: dnspython>=2.4.2
